cxbuilder_flow_config/__init__.py
cxbuilder_flow_config/py.typed
cxbuilder_flow_config/_jsii/__init__.py
cxbuilder_flow_config/_jsii/flow-config@2.1.1.jsii.tgz
cxbuilder_flow_config-2.1.1.dist-info/LICENSE
cxbuilder_flow_config-2.1.1.dist-info/METADATA
cxbuilder_flow_config-2.1.1.dist-info/WHEEL
cxbuilder_flow_config-2.1.1.dist-info/top_level.txt
cxbuilder_flow_config-2.1.1.dist-info/RECORD
