Metadata-Version: 2.1
Name: cxbuilder-flow-config
Version: 2.1.1
Summary: Amazon Connect third-party app for configuring variables and prompts in Connect contact flows
Home-page: https://github.com/cxbuilder/flow-config#readme
Author: CXBuilder<ivan@cxbuilder.ai>
License: MIT
Project-URL: Source, https://github.com/cxbuilder/flow-config.git
Classifier: Intended Audience :: Developers
Classifier: Operating System :: OS Independent
Classifier: Programming Language :: JavaScript
Classifier: Programming Language :: Python :: 3 :: Only
Classifier: Programming Language :: Python :: 3.9
Classifier: Programming Language :: Python :: 3.10
Classifier: Programming Language :: Python :: 3.11
Classifier: Typing :: Typed
Classifier: Development Status :: 5 - Production/Stable
Classifier: License :: OSI Approved
Classifier: Framework :: AWS CDK
Classifier: Framework :: AWS CDK :: 2
Requires-Python: ~=3.9
License-File: LICENSE
Requires-Dist: aws-cdk-lib==2.194.0
Requires-Dist: constructs<11.0.0,>=10.0.0
Requires-Dist: jsii<2.0.0,>=1.112.0
Requires-Dist: publication>=0.0.3
Requires-Dist: typeguard<4.3.0,>=2.13.3
